pytholic/__init__.py
pytholic/icons.py
pytholic/prayers.py
pytholic/variety.py
pytholic/bible/__init__.py
pytholic/bible/_books.py
pytholic/bible/_exceptions.py
pytholic/bible/bible.py
pytholic-1.0.1.dist-info/LICENSE.txt
pytholic-1.0.1.dist-info/METADATA
pytholic-1.0.1.dist-info/WHEEL
pytholic-1.0.1.dist-info/top_level.txt
pytholic-1.0.1.dist-info/RECORD
